pgrest/__init__.py
pgrest/__version__.py
pgrest/_sync_client.py
pgrest/async_client.py
pgrest/base_client.py
pgrest/constants.py
pgrest/query.py
pgrest/request_builder.py
pgrest/utils.py
pgrest-0.7.0.dist-info/LICENSE
pgrest-0.7.0.dist-info/WHEEL
pgrest-0.7.0.dist-info/METADATA
pgrest-0.7.0.dist-info/RECORD
